hyfetcher/__cli__.py
hyfetcher/__init__.py
hyfetcher/_version.py
hyfetcher/agents/__init__.py
hyfetcher/chains/__init__.py
hyfetcher/chains/extraction.py
hyfetcher/conf/__init__.py
hyfetcher/conf/about/hyfetcher.yaml
hyfetcher/conf/fetcher/sample.yaml
hyfetcher/conf/llm/__init__.yaml
hyfetcher/conf/llm/gpt35.yaml
hyfetcher/conf/llm/gpt4.yaml
hyfetcher/conf/llm/openai.yaml
hyfetcher/fetcher/__init__.py
hyfetcher/fetcher/base.py
hyfetcher/fetcher/sample.py
hyfetcher/fetcher/schemas.py
hyfetcher/llms/__init__.py
hyfetcher/llms/openai.py
hyfetcher/py.typed
hyfetcher/tools/__init__.py
hyfi_fetcher-0.2.2.dist-info/LICENSE
hyfi_fetcher-0.2.2.dist-info/METADATA
hyfi_fetcher-0.2.2.dist-info/WHEEL
hyfi_fetcher-0.2.2.dist-info/entry_points.txt
hyfi_fetcher-0.2.2.dist-info/RECORD
