Metadata-Version: 2.1
Name: hyfi-fetcher
Version: 0.2.2
Summary: HyFI-Fetcher is a Python package for programmatically scraping websites to extract various data, serving as a plugin for HyFI.
Home-page: https://hyfi-fetcher.entelecheia.ai
License: MIT
Author: Young Joon Lee
Author-email: entelecheia@hotmail.com
Requires-Python: >=3.9,<3.13
Classifier: License :: OSI Approved :: MIT License
Classifier: Programming Language :: Python :: 3
Classifier: Programming Language :: Python :: 3.9
Classifier: Programming Language :: Python :: 3.10
Classifier: Programming Language :: Python :: 3.11
Classifier: Programming Language :: Python :: 3.12
Requires-Dist: click (>=8.1.3,<9.0.0)
Requires-Dist: hyfi (>=1.36.3,<2.0.0)
Requires-Dist: langchain (>=0.1.16,<0.2.0)
Requires-Dist: openai (>=1.21.2,<2.0.0)
Requires-Dist: playwright (>=1.43.0,<2.0.0)
Project-URL: Repository, https://github.com/entelecheia/hyfi-fetcher
